Simon/ColumnProcessor.py
Simon/DataFlattener.py
Simon/DataGenerator.py
Simon/Encoder.py
Simon/FakeDataDescriptor.py
Simon/LengthStandardizer.py
Simon/Simon.py
Simon/SimonRestListener.py
Simon/__init__.py
Simon/types.json
Simon/penny/__init__.py
Simon/penny/geo_lookup.py
Simon/penny/guesser.py
Simon/penny/utils.py
Simon/penny/value_checks.py
d3m_simon-1.2.6.dist-info/LICENSE
d3m_simon-1.2.6.dist-info/METADATA
d3m_simon-1.2.6.dist-info/WHEEL
d3m_simon-1.2.6.dist-info/top_level.txt
d3m_simon-1.2.6.dist-info/RECORD
